{
    "domains": {
        "g0v.us": [
            [
                "CNAME",
                "git.github.io"
            ]
        ],
        "www.g0v.us": [
            [
                "CNAME",
                "git.github.io"
            ]
        ],
        "_github-pages-challenge-ronnywang.g0v.us": [
            [
                "TXT",
                "0ba684cbbe173160baeb04c8a88b1b"
            ]
        ]
    },
    "repository": "https://github.com/g0v/g0v.asia",
    "maintainer": [
        "zbryikt"
    ]
}
